astmareq2/__init__.py
astmareq2-1.0.dist-info/METADATA
astmareq2-1.0.dist-info/WHEEL
astmareq2-1.0.dist-info/top_level.txt
astmareq2-1.0.dist-info/RECORD
