Metadata-Version: 2.1
Name: astmareq2
Version: 1.0
Summary: package with astma codes
Author: Black_shark
